{
  "type": "Feature",
  "properties": {
    "wof:name":"Testing wof:concordances encoding",
    "wof:placetype":"venue"
},
  "geometry": {"coordinates":[-73.988457,40.74091],"type":"Point"}
}