{
  "type": "Feature",
  "properties": {
    "wof:name":"Fillmore",
    "wof:placetype":"neighbourhood"
},
  "geometry": {"coordinates":[-122.43176962429824,37.77988841078581],"type":"Point"}
}