{
  "type": "Feature",
  "properties": {
    "addr:full":"San Francisco, CA, USA",
    "iso:country":"US",
    "name:eng_x_preferred":[
        "\ud83d\ude0e"
    ],
    "wof:name":"\ud83d\ude0e",
    "wof:placetype":"venue"
},
  "geometry": {"coordinates":[-122.431962,37.777872],"type":"Point"}
}