{
  "type": "Feature",
  "properties": {
    "addr:full":"San Francisco, CA, USA",
    "name:eng_x_preferred":[
        "\ud83d\ude0e"
    ],
    "wof:name":"\ud83d\ude0e",
    "wof:placetype":"venue"
},
  "geometry": {"coordinates":[-122.43127200000001,37.778008],"type":"Point"}
}